<?xml version="1.0" encoding="UTF-8"?>
<detail id="stale-lint">
  <title>Stale Lint Skill Implementation</title>
  <consumes>
    <artifact>specs/*/spec.xml (scan all spec identity headers)</artifact>
    <artifact>specs/*/dag.yaml (check existence)</artifact>
    <artifact>docs/plans/*/*/design.md (scan all design iterations)</artifact>
  </consumes>
  <produces>
    <artifact>Structured lint report (stdout, not persisted to disk)</artifact>
  </produces>

  <requirement id="fr-sl-001">
    <title>Core Module API</title>
    <description>
      A scripts/lib/stale-lint.js module MUST expose a single entry function that
      scans the project and returns a structured report of all stale-lint findings.
    </description>
    <acceptance_criteria>
      <criterion id="fr-sl-001-ac1">
        The module MUST export a function accepting projectRoot (string) and
        returning an array of finding objects, each with: rule (string), spec_id
        (string), severity ("warning"), message (string).
        <trace>REQ-F026, REQ-F027, REQ-F028</trace>
      </criterion>
      <criterion id="fr-sl-001-ac2">
        Given a project with no stale artifacts, the function MUST return an
        empty array.
        <trace>REQ-F026</trace>
      </criterion>
      <criterion id="fr-sl-001-ac3">
        The module MUST NOT throw on missing specs/ or docs/plans/ directories.
        Missing directories mean no findings for that category.
        <trace>REQ-N001</trace>
      </criterion>
    </acceptance_criteria>
  </requirement>

  <requirement id="fr-sl-002">
    <title>Design-Newer-Than-Spec Detection</title>
    <description>
      The module MUST detect when a design iteration folder is newer than the
      spec's recorded design_iteration.
    </description>
    <acceptance_criteria>
      <criterion id="fr-sl-002-ac1">
        Given specs/auth/spec.xml with design_iteration: 2026-04-01 and
        docs/plans/auth/2026-04-16/design.md existing, the module MUST return a
        finding with rule: "stale-spec", spec_id: "auth", message containing both
        dates.
        <trace>REQ-F026</trace>
      </criterion>
      <criterion id="fr-sl-002-ac2">
        The module MUST compare by folder name date (YYYY-MM-DD lexicographic),
        not by file modification timestamp.
        <trace>REQ-F026</trace>
      </criterion>
      <criterion id="fr-sl-002-ac3">
        If the spec's source/design_iteration matches the newest design folder
        date, the module MUST NOT produce a stale-spec finding for that spec.
        <trace>REQ-F026</trace>
      </criterion>
    </acceptance_criteria>
  </requirement>

  <requirement id="fr-sl-003">
    <title>Unrefined Design Detection</title>
    <description>
      The module MUST detect when a docs/plans/&lt;spec-id&gt;/ folder exists but no
      corresponding specs/&lt;spec-id&gt;/spec.xml exists.
    </description>
    <acceptance_criteria>
      <criterion id="fr-sl-003-ac1">
        Given docs/plans/new-feature/ with at least one iteration subfolder and
        no specs/new-feature/ directory, the module MUST return a finding with
        rule: "unrefined-design", spec_id: "new-feature".
        <trace>REQ-F027</trace>
      </criterion>
      <criterion id="fr-sl-003-ac2">
        An empty docs/plans/new-feature/ folder (no iteration subfolders) MUST
        NOT produce a finding. Only folders containing at least one YYYY-MM-DD
        subfolder with a design.md count.
        <trace>REQ-F027</trace>
      </criterion>
    </acceptance_criteria>
  </requirement>

  <requirement id="fr-sl-004">
    <title>Unplanned Spec Detection</title>
    <description>
      The module MUST detect when specs/&lt;spec-id&gt;/spec.xml exists but
      specs/&lt;spec-id&gt;/dag.yaml does not.
    </description>
    <acceptance_criteria>
      <criterion id="fr-sl-004-ac1">
        Given specs/auth/spec.xml exists and specs/auth/dag.yaml does not, the
        module MUST return a finding with rule: "unplanned-spec", spec_id: "auth".
        <trace>REQ-F028</trace>
      </criterion>
    </acceptance_criteria>
  </requirement>

  <requirement id="fr-sl-005">
    <title>Skill Definition</title>
    <description>
      A skill (arc-linting) MUST exist that invokes the core module and presents
      findings to the user.
    </description>
    <acceptance_criteria>
      <criterion id="fr-sl-005-ac1">
        The skill MUST be invocable via /arcforge:arc-linting.
        <trace>REQ-F026, REQ-F027, REQ-F028</trace>
      </criterion>
      <criterion id="fr-sl-005-ac2">
        When findings exist, the skill MUST present them grouped by rule type
        (stale-spec, unrefined-design, unplanned-spec) with actionable
        recommendations for each.
        <trace>REQ-F026, REQ-F027, REQ-F028</trace>
      </criterion>
      <criterion id="fr-sl-005-ac3">
        When no findings exist, the skill MUST report "no stale artifacts found".
        <trace>REQ-F026</trace>
      </criterion>
      <criterion id="fr-sl-005-ac4">
        The skill MUST support an optional spec-id argument to lint a single spec
        instead of all specs. Given /arcforge:arc-linting auth, only specs/auth/
        and docs/plans/auth/ are checked.
        <trace>REQ-F026, REQ-F027, REQ-F028</trace>
      </criterion>
      <criterion id="fr-sl-005-ac5">
        The skill's frontmatter description MUST start with "Use when" and describe
        triggering conditions only (e.g., "Use when checking for stale artifacts,
        drift between design docs and specs, or unrefined/unplanned pipeline
        stages"). The description MUST NOT summarize the skill's process or output.
        <trace>REQ-F026, REQ-F027, REQ-F028</trace>
      </criterion>
    </acceptance_criteria>
  </requirement>

  <requirement id="fr-sl-006">
    <title>No Automatic Invocation</title>
    <description>
      Stale lint MUST NOT run automatically via hooks or session start. It is
      user-initiated only.
    </description>
    <acceptance_criteria>
      <criterion id="fr-sl-006-ac1">
        No SessionStart, PreToolUse, or other hook MUST reference stale-lint
        logic. The only entry point is the arc-linting skill.
        <trace>REQ-N001</trace>
      </criterion>
    </acceptance_criteria>
  </requirement>
</detail>
